{
  "$schema": "https://jentic.com/schemas/api-meta.schema.json",
  "id": "urn:oak:jokes.one:main:1.1",
  "status": "published",
  "bundled": true,
  "info": {
    "vendor": "jokes.one",
    "apiName": "main",
    "version": "1.1",
    "oasVersion": "3.0.0",
    "license": null
  },
  "artifacts": {
    "base": "https://github.com/jentic/jentic-public-apis/tree/main/apis/openapi/jokes.one/main/1.1",
    "entry": "https://raw.githubusercontent.com/jentic/jentic-public-apis/refs/heads/main/apis/openapi/jokes.one/main/1.1/openapi.json"
  },
  "meta": {
    "timestamps": {
      "added": "2025-12-16T00:39:23+00:00",
      "updated": "2025-12-16T00:39:23+00:00"
    },
    "diagnostics": {
      "severity": {
        "errors": 2,
        "warnings": 134,
        "info": 33
      },
      "source": {
        "repair": 0,
        "validator": 152,
        "loader": 4,
        "parser": 0,
        "comparator": 0,
        "converter": 0,
        "fs": 0
      }
    },
    "references": {
      "relative": 0,
      "absolute": 0
    },
    "import": {
      "source": {
        "url": "https://raw.githubusercontent.com/jentic/jentic-public-apis/refs/heads/main/apis/openapi/jokes.one/main/1.1/openapi.json",
        "apiId": "43f194f7a426d437b953b6fbdadb551b",
        "apiVersionId": "",
        "resolvedOriginalUrl": "https://api.jokes.one/yaml/jokes.one.yaml",
        "retrievedAt": "2025-12-16T01:39:23"
      },
      "diagnostics": {
        "severity": {
          "errors": 2,
          "warnings": 134,
          "info": 29
        },
        "source": {
          "repair": 0,
          "validator": 152,
          "loader": 0,
          "parser": 0,
          "comparator": 0,
          "converter": 0,
          "fs": 0
        },
        "persistentInvalidRefs": false,
        "rewrittenInvalidRefs": false
      },
      "bundleSameAsRoot": true,
      "bundleSameAsImported": true
    }
  }
}