{
  "aid": "googleapis.com:kgsearch-v1",
  "name": "Knowledge Graph Search API",
  "type": "Index",
  "description": "Searches the Google Knowledge Graph for entities.",
  "url": "https://raw.githubusercontent.com/jentic/jentic-public-apis/refs/heads/main/apis/openapi/googleapis.com/kgsearch/v1/apis.json",
  "tags": [
    "googleapis.com",
    "kgsearch",
    "published"
  ],
  "baseUrl": "https://kgsearch.googleapis.com/",
  "created": "2025-12-16",
  "modified": "2025-12-16",
  "specificationVersion": "0.19",
  "access": "3rd-Party",
  "maintainers": [
    {
      "fn": "Jentic",
      "x-github": "jentic",
      "url": "https://github.com/jentic"
    }
  ],
  "apis": [
    {
      "aid": "googleapis.com:kgsearch-v1",
      "name": "Knowledge Graph Search API",
      "description": "Searches the Google Knowledge Graph for entities.",
      "version": "v1",
      "tags": [
        "googleapis.com",
        "kgsearch",
        "published"
      ],
      "properties": [
        {
          "type": "OpenAPI",
          "name": "OpenAPI definition",
          "url": "https://raw.githubusercontent.com/jentic/jentic-public-apis/refs/heads/main/apis/openapi/googleapis.com/kgsearch/v1/openapi.json",
          "mediaType": "application/openapi+json"
        },
        {
          "type": "GitHubRepo",
          "url": "https://github.com/jentic/jentic-public-apis/tree/main/apis/openapi/googleapis.com/kgsearch/v1"
        }
      ],
      "contact": {
        "fn": "Google",
        "url": "https://google.com"
      }
    }
  ]
}