{
  "$schema": "https://jentic.com/schemas/api-meta.schema.json",
  "id": "urn:oak:funtranslations.com:starwars:2.3",
  "status": "published",
  "bundled": true,
  "info": {
    "vendor": "funtranslations.com",
    "apiName": "starwars",
    "version": "2.3",
    "oasVersion": "3.0.0",
    "license": null
  },
  "artifacts": {
    "base": "https://github.com/jentic/jentic-public-apis/tree/main/apis/openapi/funtranslations.com/starwars/2.3",
    "entry": "https://raw.githubusercontent.com/jentic/jentic-public-apis/refs/heads/main/apis/openapi/funtranslations.com/starwars/2.3/openapi.json"
  },
  "meta": {
    "timestamps": {
      "added": "2025-12-15T19:29:14+00:00",
      "updated": "2025-12-15T19:29:14+00:00"
    },
    "diagnostics": {
      "severity": {
        "errors": 2,
        "warnings": 53,
        "info": 26
      },
      "source": {
        "repair": 0,
        "validator": 70,
        "loader": 4,
        "parser": 0,
        "comparator": 0,
        "converter": 0,
        "fs": 0
      }
    },
    "references": {
      "relative": 0,
      "absolute": 0
    },
    "import": {
      "source": {
        "url": "https://raw.githubusercontent.com/jentic/jentic-public-apis/refs/heads/main/apis/openapi/funtranslations.com/starwars/2.3/openapi.json",
        "apiId": "b7fd0b5500b7b00675a0b5240485f898",
        "apiVersionId": "",
        "resolvedOriginalUrl": "https://funtranslations.com/yaml/funtranslations.starwars.yaml",
        "retrievedAt": "2025-12-15T20:29:14"
      },
      "diagnostics": {
        "severity": {
          "errors": 2,
          "warnings": 53,
          "info": 22
        },
        "source": {
          "repair": 0,
          "validator": 70,
          "loader": 0,
          "parser": 0,
          "comparator": 0,
          "converter": 0,
          "fs": 0
        },
        "persistentInvalidRefs": false,
        "rewrittenInvalidRefs": false
      },
      "bundleSameAsRoot": true,
      "bundleSameAsImported": true
    }
  }
}