{
  "aid": "neutrinoapi.net:main-3.7.1",
  "name": "Neutrino API",
  "type": "Index",
  "description": "The general-purpose API",
  "url": "https://raw.githubusercontent.com/jentic/jentic-public-apis/refs/heads/main/apis/openapi/neutrinoapi.net/main/3.7.1/apis.json",
  "tags": [
    "neutrinoapi.net",
    "main",
    "published"
  ],
  "baseUrl": "https://neutrinoapi.net/",
  "created": "2025-12-16",
  "modified": "2025-12-16",
  "specificationVersion": "0.19",
  "access": "3rd-Party",
  "maintainers": [
    {
      "fn": "Jentic",
      "x-github": "jentic",
      "url": "https://github.com/jentic"
    }
  ],
  "apis": [
    {
      "aid": "neutrinoapi.net:main-3.7.1",
      "name": "Neutrino API",
      "description": "The general-purpose API",
      "version": "3.7.1",
      "tags": [
        "neutrinoapi.net",
        "main",
        "published"
      ],
      "properties": [
        {
          "type": "OpenAPI",
          "name": "OpenAPI definition",
          "url": "https://raw.githubusercontent.com/jentic/jentic-public-apis/refs/heads/main/apis/openapi/neutrinoapi.net/main/3.7.1/openapi.json",
          "mediaType": "application/openapi+json"
        },
        {
          "type": "GitHubRepo",
          "url": "https://github.com/jentic/jentic-public-apis/tree/main/apis/openapi/neutrinoapi.net/main/3.7.1"
        }
      ],
      "contact": {
        "fn": "Neutrino API",
        "email": "tech@neutrinoapi.com",
        "url": "https://www.neutrinoapi.com/"
      }
    }
  ]
}